LICENSE
fs_toolkit/__init__.py
fs_toolkit/base.py
fs_toolkit/exceptions.py
fs_toolkit/fstab/__init__.py
fs_toolkit/fstab/constants.py
fs_toolkit/fstab/loader.py
fs_toolkit/fstab/platform/__init__.py
fs_toolkit/fstab/platform/base.py
fs_toolkit/fstab/platform/bsd.py
fs_toolkit/fstab/platform/darwin.py
fs_toolkit/fstab/platform/linux.py
fs_toolkit/fstab/platform/openbsd.py
fs_toolkit/mounts/__init__.py
fs_toolkit/mounts/constants.py
fs_toolkit/mounts/loader.py
fs_toolkit/mounts/platform/__init__.py
fs_toolkit/mounts/platform/base.py
fs_toolkit/mounts/platform/bsd.py
fs_toolkit/mounts/platform/darwin.py
fs_toolkit/mounts/platform/linux.py
fs_toolkit/mounts/platform/openbsd.py
fs_toolkit-2.4.8.dist-info/LICENSE
fs_toolkit-2.4.8.dist-info/METADATA
fs_toolkit-2.4.8.dist-info/WHEEL
fs_toolkit-2.4.8.dist-info/RECORD
