Metadata-Version: 2.1
Name: fs-toolkit
Version: 2.4.8
Summary: Classes for filesystem usage utilities
Home-page: https://github.com/hile/fs-toolkit
License: BSD-3-Clause
Author: Ilkka Tuohela
Author-email: hile@iki.fi
Requires-Python: >=3.9,<4.0
Classifier: Environment :: Console
Classifier: License :: OSI Approved :: BSD License
Classifier: Operating System :: MacOS
Classifier: Operating System :: POSIX
Classifier: Operating System :: Unix
Classifier: Programming Language :: Python :: 3
Classifier: Programming Language :: Python :: 3.9
Classifier: Programming Language :: Python :: 3.10
Classifier: Programming Language :: Python :: 3.11
Classifier: Programming Language :: Python :: 3.10
Classifier: Programming Language :: Python :: 3.11
Classifier: Programming Language :: Python :: 3.9
Classifier: Topic :: Utilities
Requires-Dist: sys-toolkit (>=2,<3)
